cx_copilot/LICENSE
cx_copilot/__init__.py
cx_copilot/blocks/cache.py
cx_copilot/blocks/cleaner.py
cx_copilot/blocks/completion.py
cx_copilot/blocks/embedding.py
cx_copilot/blocks/tickets.py
cx_copilot/blocks/vectordb.py
cx_copilot/compound/compound.py
cx_copilot/exceptions/exceptions.py
cx_copilot/utils/eval.py
cx_copilot-0.0.12.dist-info/LICENSE
cx_copilot-0.0.12.dist-info/WHEEL
cx_copilot-0.0.12.dist-info/METADATA
cx_copilot-0.0.12.dist-info/RECORD
