Metadata-Version: 2.1
Name: cx-copilot
Version: 0.0.12
Summary: Sample Python Project for creating a new Python Module
Author-email: "Rahul S, Tanuj Tiwari" <rahul@caesarhq.com>
Requires-Python: >=3.7
Classifier: Development Status :: 3 - Alpha
Classifier: Intended Audience :: Developers
Classifier: License :: OSI Approved :: MIT License
Classifier: Programming Language :: Python :: 3 :: Only
Classifier: Programming Language :: Python :: 3.7
Classifier: Programming Language :: Python :: 3.8
Classifier: Programming Language :: Python :: 3.9
Classifier: Programming Language :: Python :: 3.10
Requires-Dist: requests~=2.28.1
Requires-Dist: pinecone-client==2.1.0
Requires-Dist: redis~=4.4.1
Requires-Dist: openai>=0.27.0
Requires-Dist: python-helpscout-v2==2.0.0
Requires-Dist: envyaml~=1.10.211231
Requires-Dist: python-intercom~=3.1.0
Requires-Dist: email_reply_parser~=0.5.12
Requires-Dist: beautifulsoup4~=4.11.1
Requires-Dist: zenpy~=2.0.25
Requires-Dist: pre-commit~=2.21.0
Requires-Dist: hikari~=2.0.0.dev115
Requires-Dist: pyspark>=3.0.0 ; extra == "spark"
Requires-Dist: bandit[toml]==1.7.4 ; extra == "test"
Requires-Dist: black==22.1.0 ; extra == "test"
Requires-Dist: check-manifest==0.48 ; extra == "test"
Requires-Dist: flake8-bugbear==22.1.11 ; extra == "test"
Requires-Dist: flake8-docstrings ; extra == "test"
Requires-Dist: flake8-formatter_junit_xml ; extra == "test"
Requires-Dist: flake8==4.0.1 ; extra == "test"
Requires-Dist: pre-commit==2.17.0 ; extra == "test"
Requires-Dist: pylint==2.12.2 ; extra == "test"
Requires-Dist: pylint_junit ; extra == "test"
Requires-Dist: pytest-cov==3.0.0 ; extra == "test"
Requires-Dist: pytest-mock<3.7.1 ; extra == "test"
Requires-Dist: pytest-runner ; extra == "test"
Requires-Dist: pytest==7.1.0 ; extra == "test"
Requires-Dist: pytest-github-actions-annotate-failures ; extra == "test"
Requires-Dist: shellcheck-py==0.8.0.4 ; extra == "test"
Project-URL: Documentation, https://github.com/caesarhq
Project-URL: Source, https://github.com/caesarhq
Project-URL: Tracker, https://github.com/caesarhq
Provides-Extra: spark
Provides-Extra: test
